hyhound/__init__.py
hyhound/_dispatch.cpython-311-arm-linux-gnueabihf.so
hyhound/_hyhound.py
hyhound/_hyhound.pyi
hyhound/_hyhound_generic.cpython-311-arm-linux-gnueabihf.so
hyhound/libnanobind-hyhound.so
hyhound/py.typed
hyhound-1.0.2a2.dist-info/METADATA
hyhound-1.0.2a2.dist-info/WHEEL
hyhound-1.0.2a2.dist-info/entry_points.txt
hyhound-1.0.2a2.dist-info/licenses/LICENSE
hyhound-1.0.2a2.dist-info/RECORD
