Metadata-Version: 2.4
Name: hyhound
Version: 1.0.2a2
Summary: Hyperbolic Householder transformations for Up- and Downdating Cholesky factorizations.
Keywords: linear-algebra,cholesky,update,downdate,matrix
Author-Email: Pieter P <pieter.p.dev@outlook.com>
License-Expression: LGPL-3.0-or-later
License-File: LICENSE
Classifier: Development Status :: 4 - Beta
Classifier: Intended Audience :: Science/Research
Classifier: Topic :: Scientific/Engineering
Classifier: Topic :: Scientific/Engineering :: Mathematics
Classifier: Programming Language :: Python :: 3
Classifier: Programming Language :: Python :: 3.9
Classifier: Programming Language :: Python :: 3.10
Classifier: Programming Language :: Python :: 3.11
Classifier: Programming Language :: Python :: 3.12
Classifier: Programming Language :: Python :: 3.13
Classifier: Programming Language :: Python :: 3.14
Classifier: Operating System :: POSIX :: Linux
Classifier: Operating System :: Microsoft :: Windows
Classifier: Operating System :: MacOS
Classifier: Typing :: Typed
Project-URL: Documentation, https://kul-optec.github.io/hyhound
Project-URL: Source, https://github.com/kul-optec/hyhound
Project-URL: Bug Tracker, https://github.com/kul-optec/hyhound/issues
Requires-Python: >=3.9
Requires-Dist: numpy<3
Provides-Extra: test
Requires-Dist: pytest<9,>=7.2.0; extra == "test"
